statistical_stocks_ta/__init__.py
statistical_stocks_ta/indicators.py
statistical_stocks_ta/patterns.py
statistical_stocks_ta/plotting.py
statistical_stocks_ta/smc.py
statistical_stocks_ta/statistical_stocks_ta.py
statistical_stocks_ta/support_resistance.py
statistical_stocks_ta-0.1.2.dist-info/LICENSE
statistical_stocks_ta-0.1.2.dist-info/METADATA
statistical_stocks_ta-0.1.2.dist-info/WHEEL
statistical_stocks_ta-0.1.2.dist-info/top_level.txt
statistical_stocks_ta-0.1.2.dist-info/RECORD
