Metadata-Version: 2.1
Name: statistical-stocks-ta
Version: 0.1.2
Summary: A python package for Statistical Stocks TA (computing patterns, ma, indicators) and data fetching.
Home-page: https://github.com/Nils-Lopez/statistical-stocks-ta
Author: Nils Lopez
Author-email: lopez.nils@doctopus.app
Classifier: Programming Language :: Python :: 3
Classifier: License :: OSI Approved :: MIT License
Classifier: Operating System :: OS Independent
Requires-Python: >=3.6
License-File: LICENSE
Requires-Dist: requests
Requires-Dist: pandas
Requires-Dist: numpy
Requires-Dist: ta
Requires-Dist: mplfinance
Requires-Dist: ccxt
Requires-Dist: scikit-learn
Requires-Dist: smartmoneyconcepts
